create_unity_package/__init__.py
create_unity_package/__main__.py
create_unity_package/create_unity_package.py
create_unity_package/templates/changelog.md
create_unity_package/templates/gitignore.txt
create_unity_package/templates/license.mit.md
create_unity_package/templates/package_documentation.md
create_unity_package/templates/readme.template.md
create_unity_package-1.0.4.dist-info/LICENSE
create_unity_package-1.0.4.dist-info/METADATA
create_unity_package-1.0.4.dist-info/WHEEL
create_unity_package-1.0.4.dist-info/entry_points.txt
create_unity_package-1.0.4.dist-info/top_level.txt
create_unity_package-1.0.4.dist-info/RECORD
