Metadata-Version: 2.1
Name: create-unity-package
Version: 1.0.4
Summary: CLI tool for generating boilerplate Unity packages
Home-page: https://github.com/ShiJbey/create_unity_package
Author: Shi Johnson-Bey
Author-email: shijbey@gmail.com
License: MIT
Project-URL: Bug Tracker, https://github.com/ShiJbey/create_unity_package/issues
Keywords: unity 3d,unity,automation,cli
Classifier: Programming Language :: Python :: 3
Classifier: License :: OSI Approved :: MIT License
Classifier: Operating System :: OS Independent
Classifier: Environment :: Console
Classifier: Intended Audience :: Developers
Classifier: Topic :: Games/Entertainment
Classifier: Typing :: Typed
Classifier: Topic :: Utilities
Requires-Python: >=3.8
License-File: LICENSE
Requires-Dist: inquirer
Requires-Dist: jinja2
